maya_toolbar.py
maya_toolbar-0.2.0.dist-info/LICENSE
maya_toolbar-0.2.0.dist-info/METADATA
maya_toolbar-0.2.0.dist-info/WHEEL
maya_toolbar-0.2.0.dist-info/top_level.txt
maya_toolbar-0.2.0.dist-info/RECORD
