Metadata-Version: 2.2
Name: maya-toolbar
Version: 0.2.0
Summary: Alternative for maya shelves
Author-email: Fabien Taxil <me@lixaft.dev>
License: MIT License
Project-URL: Repository, https://github.com/lixaft/maya-toolbar
Project-URL: Documentation, https://github.com/lixaft/maya-toolbar/blob/main/README.md
Classifier: License :: OSI Approved :: MIT License
Classifier: Programming Language :: Python :: 2
Classifier: Programming Language :: Python :: 3
Requires-Python: >=2.7
License-File: LICENSE
Requires-Dist: pyyaml
